<?xml version="1.0" encoding="UTF-8"?>
<odoo>
    <!-- LMS List view -->
    <record id="view_tree_todo_task" model="ir.ui.view">
        <field name="name">LMS Tree</field>
        <field name="model">lms.general</field>
        <field name="arch" type="xml">
            <tree>
                <field name="general_ref" />
                <field name="origin_country" />
                <field name="destination_country" />
            </tree>
        </field>
    </record>
    <!-- LMS search view -->
    <record id="view_search_todo_task" model="ir.ui.view">
        <field name="name">LMS Filters</field>
        <field name="model">lms.general</field>
        <field name="arch" type="xml">
            <search>
                <field name="general_ref" />
            </search>
        </field>
    </record>
</odoo>
